{
  "Fresh_Apple": 0,
  "Fresh_Banana": 1,
  "Fresh_Bellpepper": 2,
  "Fresh_Bittergourd": 3,
  "Fresh_Capsicum": 4,
  "Fresh_Carrot": 5,
  "Fresh_Cucumber": 6,
  "Fresh_Mango": 7,
  "Fresh_Okra": 8,
  "Fresh_Orange": 9,
  "Fresh_Potato": 10,
  "Fresh_Strawberry": 11,
  "Fresh_Tomato": 12,
  "Rotten_Apple": 13,
  "Rotten_Banana": 14,
  "Rotten_Bellpepper": 15,
  "Rotten_Bittergourd": 16,
  "Rotten_Capsicum": 17,
  "Rotten_Carrot": 18,
  "Rotten_Cucumber": 19,
  "Rotten_Mango": 20,
  "Rotten_Okra": 21,
  "Rotten_Orange": 22,
  "Rotten_Potato": 23,
  "Rotten_Strawberry": 24,
  "Rotten_Tomato": 25
}